secimtools/__init__.py
secimtools/anovaModules/__init__.py
secimtools/anovaModules/changeDFOrder.py
secimtools/anovaModules/flagSignificant.py
secimtools/anovaModules/generateDinamicCmbs.py
secimtools/anovaModules/getModelResults.py
secimtools/anovaModules/getModelResultsByGroup.py
secimtools/anovaModules/gimmeTheMissin.py
secimtools/anovaModules/parseFormula.py
secimtools/anovaModules/preProcessing.py
secimtools/anovaModules/qqPlot.py
secimtools/anovaModules/reformatData.py
secimtools/anovaModules/removeAnovaDupResults.py
secimtools/anovaModules/runANOVA.py
secimtools/anovaModules/startANOVAResults.py
secimtools/anovaModules/volcano.py
secimtools/data/__init__.py
secimtools/data/lasso_enet.R
secimtools/data/metafor_wrappers.R
secimtools/dataManager/__init__.py
secimtools/dataManager/debug.py
secimtools/dataManager/flags.py
secimtools/dataManager/interface.py
secimtools/dataManager/logger.py
secimtools/visualManager/__init__.py
secimtools/visualManager/manager_color.py
secimtools/visualManager/manager_figure.py
secimtools/visualManager/module_bar.py
secimtools/visualManager/module_box.py
secimtools/visualManager/module_distribution.py
secimtools/visualManager/module_heatmap.py
secimtools/visualManager/module_hist.py
secimtools/visualManager/module_lines.py
secimtools/visualManager/module_mmc.py
secimtools/visualManager/module_scatter.py
secimtools/visualManager/module_venn.py
secimtools-22.3.23.data/scripts/add_group_rank.py
secimtools-22.3.23.data/scripts/anova_fixed.py
secimtools-22.3.23.data/scripts/bland_altman_plot.py
secimtools-22.3.23.data/scripts/blank_feature_filtering_flags.py
secimtools-22.3.23.data/scripts/coefficient_variation_flags.py
secimtools-22.3.23.data/scripts/compare_flags.py
secimtools-22.3.23.data/scripts/compound_identification.py
secimtools-22.3.23.data/scripts/data_normalization_and_rescaling.py
secimtools-22.3.23.data/scripts/distribution_features.py
secimtools-22.3.23.data/scripts/distribution_samples.py
secimtools-22.3.23.dist-info/LICENSE
secimtools-22.3.23.dist-info/METADATA
secimtools-22.3.23.dist-info/WHEEL
secimtools-22.3.23.dist-info/top_level.txt
secimtools-22.3.23.dist-info/RECORD
