Metadata-Version: 2.1
Name: secimtools
Version: 22.3.23
Summary: 'Metabolomics tools from the SECIM project',
Home-page: https://github.com/secimTools/SECIMTools
Author: McIntyre Lab, Universify of Florida
Author-email: om@rc.ufl.edu
License: MIT
Keywords: metabolomics secim anova pca random-forest
Platform: any
Classifier: Development Status :: 5 - Production/Stable
Classifier: Environment :: Console
Classifier: Intended Audience :: Science/Research
Classifier: Operating System :: OS Independent
Classifier: License :: OSI Approved :: MIT License
Classifier: Programming Language :: Python :: 3
Classifier: Topic :: Scientific/Engineering
Classifier: Topic :: Scientific/Engineering :: Bio-Informatics
Requires-Python: >=3.7
License-File: LICENSE
Requires-Dist: biopython (>=1.70)
Requires-Dist: biothings-client (>=0.2)
Requires-Dist: lxml (>=4)
Requires-Dist: matplotlib (>=3.2.0)
Requires-Dist: matplotlib-venn
Requires-Dist: numpy (>=1.18)
Requires-Dist: palettable (>=3.3.0)
Requires-Dist: pandas (>=1.0)
Requires-Dist: patsy (>=0.5)
Requires-Dist: pymc (>=2.3)
Requires-Dist: rpy2 (>=3.1)
Requires-Dist: scikit-learn (>=0.22)
Requires-Dist: scipy (>=1.4)
Requires-Dist: seaborn (>=0.10)
Requires-Dist: statsmodels (>=0.11)
Requires-Dist: upsetplot (>=0.6)
